README
setup.py
corkscrew/__init__.py
corkscrew/app.py
corkscrew/blueprint.py
corkscrew/comet.py
corkscrew/core.py
corkscrew/dir_index.py
corkscrew/exceptions.py
corkscrew/favicon.py
corkscrew/plumbing.py
corkscrew/proxy.py
corkscrew/reflect.py
corkscrew/runner.py
corkscrew/settings.py
corkscrew/util.py
corkscrew/version.py
corkscrew.egg-info/PKG-INFO
corkscrew.egg-info/SOURCES.txt
corkscrew.egg-info/dependency_links.txt
corkscrew.egg-info/entry_points.txt
corkscrew.egg-info/requires.txt
corkscrew.egg-info/top_level.txt