Metadata-Version: 1.0
Name: corkscrew
Version: 0.121
Summary: ooviews, settings, and basic authentication for flask
Home-page: https://github.com/mattvonrocketstein/corkscrew/
Author: mattvonrocketstein
Author-email: $author@gmail
License: UNKNOWN
Keywords: flask
Platform: UNKNOWN
